nerb/__init__.py
nerb/named_entities.py
nerb/regex_builder.py
nerb/utils.py
nerb-0.0.4.dist-info/LICENSE
nerb-0.0.4.dist-info/METADATA
nerb-0.0.4.dist-info/WHEEL
nerb-0.0.4.dist-info/top_level.txt
nerb-0.0.4.dist-info/RECORD
